LICENSE
polyglot_piranha.pyi
NOTICE
polyglot_piranha/__init__.pyi
polyglot_piranha/__init__.py
polyglot_piranha/py.typed
polyglot_piranha/polyglot_piranha.cpython-312-darwin.so
polyglot_piranha-0.4.6.dist-info/RECORD
polyglot_piranha-0.4.6.dist-info/WHEEL
polyglot_piranha-0.4.6.dist-info/METADATA
polyglot_piranha-0.4.6.dist-info/licenses/LICENSE
polyglot_piranha-0.4.6.dist-info/licenses/NOTICE
