Metadata-Version: 2.4
Name: polyglot_piranha
Version: 0.4.6
Requires-Dist: pytest>=8.0 ; extra == 'dev'
Provides-Extra: dev
License-File: LICENSE
License-File: NOTICE
Summary: Polyglot Piranha is a library for performing structural find and replace with deep cleanup.
Keywords: refactoring,code update,structural find-replace,structural search and replace,structural search
Author: Uber Technologies Inc.
License-Expression: Apache-2.0
Requires-Python: >=3.8
Project-URL: homepage, https://github.com/uber/piranha
Project-URL: documentation, https://github.com/uber/piranha
Project-URL: repository, https://github.com/uber/piranha
